flask_geo/__init__.py
flask_geo/adapters.py
flask_geo/domain.py
flask_geo/fields.py
flask_geo/validators.py
flask_geo/api/__init__.py
flask_geo/api/views.py
flask_geo-1.0.5.dist-info/LICENSE
flask_geo-1.0.5.dist-info/METADATA
flask_geo-1.0.5.dist-info/WHEEL
flask_geo-1.0.5.dist-info/top_level.txt
flask_geo-1.0.5.dist-info/RECORD
